image_cli/__init__.py
image_cli/command_line_convert.py
image_cli-0.0.0.2.dist-info/LICENSE.txt
image_cli-0.0.0.2.dist-info/METADATA
image_cli-0.0.0.2.dist-info/WHEEL
image_cli-0.0.0.2.dist-info/entry_points.txt
image_cli-0.0.0.2.dist-info/top_level.txt
image_cli-0.0.0.2.dist-info/RECORD
