Metadata-Version: 2.1
Name: image-cli
Version: 0.0.0.2
Summary: UNKNOWN
Home-page: https://github.com/jpleorx/image-cli
Author: Leo Ertuna
Author-email: leo.ertuna@gmail.com
License: Creative Commons Attribution-NonCommercial-NoDerivatives 4.0 International Public License
Download-URL: https://pypi.org/project/image-cli/
Platform: UNKNOWN
License-File: LICENSE.txt
Requires-Dist: argparse
Requires-Dist: colorama
Requires-Dist: tekleo-common-utils
